Workbook
Name Category: Lookup_Tables!$B$2:$B$7
Name Category: Cleaned_Data!$H$2:$H$1001
Name Category_Fetched: Cleaned_Data!$G$2:$G$1001
Name Cost: Lookup_Tables!$C$2:$C$7
Name Cost_Price: Cleaned_Data!$M$2:$M$1001
Name Discount: Cleaned_Data!$K$2:$K$1001
Name Discount_Fixed: Cleaned_Data!$L$2:$L$1001
Name Order_Date: Cleaned_Data!$B$2:$B$1001
Name Order_ID: Cleaned_Data!$A$2:$A$1001
Name Product: Lookup_Tables!$A$2:$A$7
Name Product: Cleaned_Data!$F$2:$F$1001
Name Quantity: Cleaned_Data!$I$2:$I$1001
Name Region: Lookup_Tables!$A$10:$A$13
Name Region: Cleaned_Data!$C$2:$C$1001
Name Salesperson: Cleaned_Data!$E$2:$E$1001
Name Slicer_Category_Fetched: #N/A
Name Slicer_Region: #N/A
Name Slicer_Salesperson: #N/A
Name State: Cleaned_Data!$D$2:$D$1001
Name Target: Lookup_Tables!$B$10:$B$13
Name Unit_Price: Cleaned_Data!$J$2:$J$1001

Sheet Pivot_Region
A3: Region | B3: Sum of Net Sales | C3: Sum of Profit
A4: West | B4: 35441355 | C4: 14659572
A5: East | B5: 34750454 | C5: 14298080
A6: South | B6: 33255425 | C6: 13234378
A7: North | B7: 31196598 | C7: 12740410
A8: Grand Total | B8: 1.3464383e+08 | C8: 54932439
B9: =GETPIVOTDATA("Sum of Net Sales",$A$3) -> 1.3464383e+08 | C9: =GETPIVOTDATA("Sum of Profit",$A$3) -> 54932439
A12: Profit Margin | B12: =C9/B9 -> 0.40798334

Sheet Pivot_Monthly
A3: Row Labels | B3: Sum of Net Sales
A4: 2024 | B4: 1.3464383e+08
A5: Jan | B5: 12049850
A6: Feb | B6: 11624511
A7: Mar | B7: 11738510
A8: Apr | B8: 11563072
A9: May | B9: 12858819
A10: Jun | B10: 10720336
A11: Jul | B11: 9789583.2
A12: Aug | B12: 10397072
A13: Sep | B13: 8724617.5
A14: Oct | B14: 11253295
A15: Nov | B15: 12412820
... A17: Grand Total | B17: 1.3464383e+08

Sheet Pivot_Top_Products
A3: Row Labels | B3: Sum of Net Sales
A4: Laptop | B4: 24677543
A5: Desk | B5: 23970747
A6: Mouse | B6: 23393985
A7: Printer | B7: 23082613
A8: Monitor | B8: 21632257
A9: Grand Total | B9: 1.1675715e+08

Sheet Pivot_Salesperson
A3: Row Labels | B3: Sum of Profit | C3: Sum of Net Sales
A4: Rahul | B4: 11643235 | C4: 27582502
A5: Amit | B5: 11354836 | C5: 27419885
A6: Karan | B6: 11317797 | C6: 26856380
A7: Neha | B7: 10250730 | C7: 26655418
A8: Priya | B8: 10365842 | C8: 26129647
A9: Grand Total | B9: 54932439 | C9: 1.3464383e+08

Sheet Dashboard
F13: =

Sheet Cleaned_Data
A1: Order ID | B1: Order Date | C1: Region | D1: State | E1: Salesperson | F1: Product | G1: Category_Fetched | H1: Category | I1: Quantity | J1: Unit Price | K1: Discount | L1: Discount_Fixed | M1: Cost Price | N1: Total Sales | O1: Net Sales | P1: Total Cost | Q1: Profit | R1: Profit Margin
A2: ORD0001 | B2: 45503 | C2: East | D2: MH | E2: Rahul | F2: Chair | G2: =INDEX(Lookup_Tables!$B$1:$B$7,MATCH(Cleaned_Data!F2,Lookup_Tables!$A$1:$A$7,0)) -> Furniture | H2: Furniture | I2: 8 | J2: 25761 | K2: 0.05 | L2: =IF(ISBLANK(K2),0,K2) -> 0.05 | M2: 29955 | N2: =I2*J2 -> 206088 | O2: =N2-(N2*L2) -> 195783.6 | P2: =I2*IFERROR(_xlfn.XLOOKUP(F2,Lookup_Tables!Product,Cost),0) -> 106168 | Q2: =O2-P2 -> 89615.6 | R2: =Q2/O2 -> 0.45772782
A3: ORD0002 | B3: 45527 | C3: West | D3: RJ | E3: Neha | F3: Laptop | G3: =INDEX(Lookup_Tables!$B$1:$B$7,MATCH(Cleaned_Data!F3,Lookup_Tables!$A$1:$A$7,0)) -> Electronics | H3: Electronics | I3: 3 | J3: 21400 | L3: =IF(ISBLANK(K3),0,K3) -> 0 | M3: 6742 | N3: =I3*J3 -> 64200 | O3: =N3-(N3*L3) -> 64200 | P3: =I3*IFERROR(_xlfn.XLOOKUP(F3,Lookup_Tables!Product,Cost),0) -> 57795 | Q3: =O3-P3 -> 6405 | R3: =Q3/O3 -> 0.099766355
A4: ORD0003 | B4: 45624 | C4: East | D4: GJ | E4: Karan | F4: Laptop | G4: =INDEX(Lookup_Tables!$B$1:$B$7,MATCH(Cleaned_Data!F4,Lookup_Tables!$A$1:$A$7,0)) -> Electronics | H4: Electronics | I4: 6 | J4: 40298 | L4: =IF(ISBLANK(K4),0,K4) -> 0 | N4: =I4*J4 -> 241788 | O4: =N4-(N4*L4) -> 241788 | P4: =I4*IFERROR(_xlfn.XLOOKUP(F4,Lookup_Tables!Product,Cost),0) -> 115590 | Q4: =O4-P4 -> 126198 | R4: =Q4/O4 -> 0.52193657
A5: ORD0004 | B5: 45311 | C5: North | D5: MH | E5: Rahul | F5: Monitor | G5: =INDEX(Lookup_Tables!$B$1:$B$7,MATCH(Cleaned_Data!F5,Lookup_Tables!$A$1:$A$7,0)) -> Electronics | H5: Electronics | I5: 9 | J5: 1098 | L5: =IF(ISBLANK(K5),0,K5) -> 0 | M5: 7334 | N5: =I5*J5 -> 9882 | O5: =N5-(N5*L5) -> 9882 | P5: =I5*IFERROR(_xlfn.XLOOKUP(F5,Lookup_Tables!Product,Cost),0) -> 25992 | Q5: =O5-P5 -> -16110 | R5: =Q5/O5 -> -1.6302368
A6: ORD0005 | B6: 45632 | C6: West | D6: RJ | E6: Karan | F6: Chair | G6: =INDEX(Lookup_Tables!$B$1:$B$7,MATCH(Cleaned_Data!F6,Lookup_Tables!$A$1:$A$7,0)) -> Furniture | H6: Furniture | I6: 4 | J6: 15968 | L6: =IF(ISBLANK(K6),0,K6) -> 0 | N6: =I6*J6 -> 63872 | O6: =N6-(N6*L6) -> 63872 | P6: =I6*IFERROR(_xlfn.XLOOKUP(F6,Lookup_Tables!Product,Cost),0) -> 53084 | Q6: =O6-P6 -> 10788 | R6: =Q6/O6 -> 0.1689003
A7: ORD0006 | B7: 45339 | C7: West | D7: RJ | E7: Amit | F7: Printer | G7: =INDEX(Lookup_Tables!$B$1:$B$7,MATCH(Cleaned_Data!F7,Lookup_Tables!$A$1:$A$7,0)) -> Electronics | H7: Electronics | I7: 10 | J7: 36961 | K7: 0.05 | L7: =IF(ISBLANK(K7),0,K7) -> 0.05 | M7: 16608 | N7: =I7*J7 -> 369610 | O7: =N7-(N7*L7) -> 351129.5 | P7: =I7*IFERROR(_xlfn.XLOOKUP(F7,Lookup_Tables!Product,Cost),0) -> 73840 | Q7: =O7-P7 -> 277289.5 | R7: =Q7/O7 -> 0.78970722
A8: ORD0007 | B8: 45618 | C8: North | D8: MH | E8: Amit | F8: Monitor | G8: =INDEX(Lookup_Tables!$B$1:$B$7,MATCH(Cleaned_Data!F8,Lookup_Tables!$A$1:$A$7,0)) -> Electronics | H8: Electronics | I8: 3 | J8: 1683 | L8: =IF(ISBLANK(K8),0,K8) -> 0 | M8: 25507 | N8: =I8*J8 -> 5049 | O8: =N8-(N8*L8) -> 5049 | P8: =I8*IFERROR(_xlfn.XLOOKUP(F8,Lookup_Tables!Product,Cost),0) -> 8664 | Q8: =O8-P8 -> -3615 | R8: =Q8/O8 -> -0.71598336
A9: ORD0008 | B9: 45476 | C9: South | D9: KA | E9: Amit | F9: Printer | G9: =INDEX(Lookup_Tables!$B$1:$B$7,MATCH(Cleaned_Data!F9,Lookup_Tables!$A$1:$A$7,0)) -> Electronics | H9: Electronics | I9: 2 | J9: 6047 | K9: 0.05 | L9: =IF(ISBLANK(K9),0,K9) -> 0.05 | N9: =I9*J9 -> 12094 | O9: =N9-(N9*L9) -> 11489.3 | P9: =I9*IFERROR(_xlfn.XLOOKUP(F9,Lookup_Tables!Product,Cost),0) -> 14768 | Q9: =O9-P9 -> -3278.7 | R9: =Q9/O9 -> -0.28536987
A10: ORD0009 | B10: 45530 | C10: North | D10: MH | E10: Amit | F10: Mouse | G10: =INDEX(Lookup_Tables!$B$1:$B$7,MATCH(Cleaned_Data!F10,Lookup_Tables!$A$1:$A$7,0)) -> Electronics | H10: Electronics | I10: 2 | J10: 3101 | K10: 0.1 | L10: =IF(ISBLANK(K10),0,K10) -> 0.1 | M10: 23538 | N10: =I10*J10 -> 6202 | O10: =N10-(N10*L10) -> 5581.8 | P10: =I10*IFERROR(_xlfn.XLOOKUP(F10,Lookup_Tables!Product,Cost),0) -> 56092 | Q10: =O10-P10 -> -50510.2 | R10: =Q10/O10 -> -9.0490881
A11: ORD0010 | B11: 45413 | C11: West | D11: MH | E11: Neha | F11: Printer | G11: =INDEX(Lookup_Tables!$B$1:$B$7,MATCH(Cleaned_Data!F11,Lookup_Tables!$A$1:$A$7,0)) -> Electronics | H11: Electronics | I11: 8 | J11: 41602 | K11: 0 | L11: =IF(ISBLANK(K11),0,K11) -> 0 | M11: 29885 | N11: =I11*J11 -> 332816 | O11: =N11-(N11*L11) -> 332816 | P11: =I11*IFERROR(_xlfn.XLOOKUP(F11,Lookup_Tables!Product,Cost),0) -> 59072 | Q11: =O11-P11 -> 273744 | R11: =Q11/O11 -> 0.82250853
A12: ORD0011 | B12: 45649 | C12: West | D12: GJ | E12: Karan | F12: Laptop | G12: =INDEX(Lookup_Tables!$B$1:$B$7,MATCH(Cleaned_Data!F12,Lookup_Tables!$A$1:$A$7,0)) -> Electronics | H12: Electronics | I12: 2 | J12: 17931 | K12: 0.1 | L12: =IF(ISBLANK(K12),0,K12) -> 0.1 | N12: =I12*J12 -> 35862 | O12: =N12-(N12*L12) -> 32275.8 | P12: =I12*IFERROR(_xlfn.XLOOKUP(F12,Lookup_Tables!Product,Cost),0) -> 38530 | Q12: =O12-P12 -> -6254.2 | R12: =Q12/O12 -> -0.19377366
A13: ORD0012 | B13: 45443 | C13: West | D13: TN | E13: Rahul | F13: Printer | G13: =INDEX(Lookup_Tables!$B$1:$B$7,MATCH(Cleaned_Data!F13,Lookup_Tables!$A$1:$A$7,0)) -> Electronics | H13: Electronics | I13: 3 | J13: 571 | K13: 0.1 | L13: =IF(ISBLANK(K13),0,K13) -> 0.1 | N13: =I13*J13 -> 1713 | O13: =N13-(N13*L13) -> 1541.7 | P13: =I13*IFERROR(_xlfn.XLOOKUP(F13,Lookup_Tables!Product,Cost),0) -> 22152 | Q13: =O13-P13 -> -20610.3 | R13: =Q13/O13 -> -13.368554
A14: ORD0013 | B14: 45423 | C14: West | D14: MH | E14: Karan | F14: Chair | G14: =INDEX(Lookup_Tables!$B$1:$B$7,MATCH(Cleaned_Data!F14,Lookup_Tables!$A$1:$A$7,0)) -> Furniture | H14: Furniture | I14: 9 | J14: 28406 | K14: 0.1 | L14: =IF(ISBLANK(K14),0,K14) -> 0.1 | N14: =I14*J14 -> 255654 | O14: =N14-(N14*L14) -> 230088.6 | P14: =I14*IFERROR(_xlfn.XLOOKUP(F14,Lookup_Tables!Product,Cost),0) -> 119439 | Q14: =O14-P14 -> 110649.6 | R14: =Q14/O14 -> 0.48089997
A15: ORD0014 | B15: 45400 | C15: North | D15: GJ | E15: Neha | F15: Laptop | G15: =INDEX(Lookup_Tables!$B$1:$B$7,MATCH(Cleaned_Data!F15,Lookup_Tables!$A$1:$A$7,0)) -> Electronics | H15: Electronics | I15: 6 | J15: 39809 | L15: =IF(ISBLANK(K15),0,K15) -> 0 | M15: 7704 | N15: =I15*J15 -> 238854 | O15: =N15-(N15*L15) -> 238854 | P15: =I15*IFERROR(_xlfn.XLOOKUP(F15,Lookup_Tables!Product,Cost),0) -> 115590 | Q15: =O15-P15 -> 123264 | R15: =Q15/O15 -> 0.51606421
A16: ORD0015 | B16: 45549 | C16: East | D16: GJ | E16: Karan | F16: Chair | G16: =INDEX(Lookup_Tables!$B$1:$B$7,MATCH(Cleaned_Data!F16,Lookup_Tables!$A$1:$A$7,0)) -> Furniture | H16: Furniture | I16: 3 | J16: 17089 | K16: 0.05 | L16: =IF(ISBLANK(K16),0,K16) -> 0.05 | N16: =I16*J16 -> 51267 | O16: =N16-(N16*L16) -> 48703.65 | P16: =I16*IFERROR(_xlfn.XLOOKUP(F16,Lookup_Tables!Product,Cost),0) -> 39813 | Q16: =O16-P16 -> 8890.65 | R16: =Q16/O16 -> 0.18254587
A17: ORD0016 | B17: 45401 | C17: East | D17: RJ | E17: Priya | F17: Monitor | G17: =INDEX(Lookup_Tables!$B$1:$B$7,MATCH(Cleaned_Data!F17,Lookup_Tables!$A$1:$A$7,0)) -> Electronics | H17: Electronics | I17: 9 | J17: 24048 | K17: 0 | L17: =IF(ISBLANK(K17),0,K17) -> 0 | N17: =I17*J17 -> 216432 | O17: =N17-(N17*L17) -> 216432 | P17: =I17*IFERROR(_xlfn.XLOOKUP(F17,Lookup_Tables!Product,Cost),0) -> 25992 | Q17: =O17-P17 -> 190440 | R17: =Q17/O17 -> 0.87990685
A18: ORD0017 | B18: 45342 | C18: North | D18: MH | E18: Neha | F18: Desk | G18: =INDEX(Lookup_Tables!$B$1:$B$7,MATCH(Cleaned_Data!F18,Lookup_Tables!$A$1:$A$7,0)) -> Furniture | H18: Furniture | I18: 6 | J18: 6121 | K18: 0 | L18: =IF(ISBLANK(K18),0,K18) -> 0 | M18: 8273 | N18: =I18*J18 -> 36726 | O18: =N18-(N18*L18) -> 36726 | P18: =I18*IFERROR(_xlfn.XLOOKUP(F18,Lookup_Tables!Product,Cost),0) -> 78240 | Q18: =O18-P18 -> -41514 | R18: =Q18/O18 -> -1.1303709
A19: ORD0018 | B19: 45388 | C19: North | D19: DL | E19: Neha | F19: Laptop | G19: =INDEX(Lookup_Tables!$B$1:$B$7,MATCH(Cleaned_Data!F19,Lookup_Tables!$A$1:$A$7,0)) -> Electronics | H19: Electronics | I19: 8 | J19: 29203 | K19: 0.05 | L19: =IF(ISBLANK(K19),0,K19) -> 0.05 | N19: =I19*J19 -> 233624 | O19: =N19-(N19*L19) -> 221942.8 | P19: =I19*IFERROR(_xlfn.XLOOKUP(F19,Lookup_Tables!Product,Cost),0) -> 154120 | Q19: =O19-P19 -> 67822.8 | R19: =Q19/O19 -> 0.30558684
A20: ORD0019 | B20: 45570 | C20: East | D20: GJ | E20: Neha | F20: Printer | G20: =INDEX(Lookup_Tables!$B$1:$B$7,MATCH(Cleaned_Data!F20,Lookup_Tables!$A$1:$A$7,0)) -> Electronics | H20: Electronics | I20: 6 | J20: 25953 | L20: =IF(ISBLANK(K20),0,K20) -> 0 | N20: =I20*J20 -> 155718 | O20: =N20-(N20*L20) -> 155718 | P20: =I20*IFERROR(_xlfn.XLOOKUP(F20,Lookup_Tables!Product,Cost),0) -> 44304 | Q20: =O20-P20 -> 111414 | R20: =Q20/O20 -> 0.71548569
A21: ORD0020 | B21: 45412 | C21: North | D21: GJ | E21: Karan | F21: Chair | G21: =INDEX(Lookup_Tables!$B$1:$B$7,MATCH(Cleaned_Data!F21,Lookup_Tables!$A$1:$A$7,0)) -> Furniture | H21: Furniture | I21: 9 | J21: 38450 | K21: 0 | L21: =IF(ISBLANK(K21),0,K21) -> 0 | N21: =I21*J21 -> 346050 | O21: =N21-(N21*L21) -> 346050 | P21: =I21*IFERROR(_xlfn.XLOOKUP(F21,Lookup_Tables!Product,Cost),0) -> 119439 | Q21: =O21-P21 -> 226611 | R21: =Q21/O21 -> 0.65485046
A22: ORD0021 | B22: 45626 | C22: West | D22: GJ | E22: Neha | F22: Printer | G22: =INDEX(Lookup_Tables!$B$1:$B$7,MATCH(Cleaned_Data!F22,Lookup_Tables!$A$1:$A$7,0)) -> Electronics | H22: Electronics | I22: 10 | J22: 14948 | K22: 0.05 | L22: =IF(ISBLANK(K22),0,K22) -> 0.05 | M22: 29773 | N22: =I22*J22 -> 149480 | O22: =N22-(N22*L22) -> 142006 | P22: =I22*IFERROR(_xlfn.XLOOKUP(F22,Lookup_Tables!Product,Cost),0) -> 73840 | Q22: =O22-P22 -> 68166 | R22: =Q22/O22 -> 0.48002197
A23: ORD0022 | B23: 45491 | C23: West | D23: DL | E23: Rahul | F23: Desk | G23: =INDEX(Lookup_Tables!$B$1:$B$7,MATCH(Cleaned_Data!F23,Lookup_Tables!$A$1:$A$7,0)) -> Furniture | H23: Furniture | I23: 10 | J23: 11429 | K23: 0.05 | L23: =IF(ISBLANK(K23),0,K23) -> 0.05 | N23: =I23*J23 -> 114290 | O23: =N23-(N23*L23) -> 108575.5 | P23: =I23*IFERROR(_xlfn.XLOOKUP(F23,Lookup_Tables!Product,Cost),0) -> 130400 | Q23: =O23-P23 -> -21824.5 | R23: =Q23/O23 -> -0.20100759
A24: ORD0023 | B24: 45479 | C24: East | D24: DL | E24: Priya | F24: Mouse | G24: =INDEX(Lookup_Tables!$B$1:$B$7,MATCH(Cleaned_Data!F24,Lookup_Tables!$A$1:$A$7,0)) -> Electronics | H24: Electronics | I24: 5 | J24: 11682 | K24: 0.1 | L24: =IF(ISBLANK(K24),0,K24) -> 0.1 | N24: =I24*J24 -> 58410 | O24: =N24-(N24*L24) -> 52569 | P24: =I24*IFERROR(_xlfn.XLOOKUP(F24,Lookup_Tables!Product,Cost),0) -> 140230 | Q24: =O24-P24 -> -87661 | R24: =Q24/O24 -> -1.6675417
A25: ORD0024 | B25: 45415 | C25: West | D25: MH | E25: Karan | F25: Printer | G25: =INDEX(Lookup_Tables!$B$1:$B$7,MATCH(Cleaned_Data!F25,Lookup_Tables!$A$1:$A$7,0)) -> Electronics | H25: Electronics | I25: 1 | J25: 43628 | K25: 0.05 | L25: =IF(ISBLANK(K25),0,K25) -> 0.05 | N25: =I25*J25 -> 43628 | O25: =N25-(N25*L25) -> 41446.6 | P25: =I25*IFERROR(_xlfn.XLOOKUP(F25,Lookup_Tables!Product,Cost),0) -> 7384 | Q25: =O25-P25 -> 34062.6 | R25: =Q25/O25 -> 0.82184305
A26: ORD0025 | B26: 45349 | C26: West | D26: TN | E26: Neha | F26: Monitor | G26: =INDEX(Lookup_Tables!$B$1:$B$7,MATCH(Cleaned_Data!F26,Lookup_Tables!$A$1:$A$7,0)) -> Electronics | H26: Electronics | I26: 2 | J26: 49900 | K26: 0 | L26: =IF(ISBLANK(K26),0,K26) -> 0 | N26: =I26*J26 -> 99800 | O26: =N26-(N26*L26) -> 99800 | P26: =I26*IFERROR(_xlfn.XLOOKUP(F26,Lookup_Tables!Product,Cost),0) -> 5776 | Q26: =O26-P26 -> 94024 | R26: =Q26/O26 -> 0.94212425
A27: ORD0026 | B27: 45618 | C27: East | D27: GJ | E27: Amit | F27: Desk | G27: =INDEX(Lookup_Tables!$B$1:$B$7,MATCH(Cleaned_Data!F27,Lookup_Tables!$A$1:$A$7,0)) -> Furniture | H27: Furniture | I27: 9 | J27: 25307 | L27: =IF(ISBLANK(K27),0,K27) -> 0 | M27: 7356 | N27: =I27*J27 -> 227763 | O27: =N27-(N27*L27) -> 227763 | P27: =I27*IFERROR(_xlfn.XLOOKUP(F27,Lookup_Tables!Product,Cost),0) -> 117360 | Q27: =O27-P27 -> 110403 | R27: =Q27/O27 -> 0.48472755
A28: ORD0027 | B28: 45655 | C28: East | D28: RJ | E28: Rahul | F28: Monitor | G28: =INDEX(Lookup_Tables!$B$1:$B$7,MATCH(Cleaned_Data!F28,Lookup_Tables!$A$1:$A$7,0)) -> Electronics | H28: Electronics | I28: 9 | J28: 47015 | K28: 0 | L28: =IF(ISBLANK(K28),0,K28) -> 0 | M28: 27705 | N28: =I28*J28 -> 423135 | O28: =N28-(N28*L28) -> 423135 | P28: =I28*IFERROR(_xlfn.XLOOKUP(F28,Lookup_Tables!Product,Cost),0) -> 25992 | Q28: =O28-P28 -> 397143 | R28: =Q28/O28 -> 0.9385728
A29: ORD0028 | B29: 45638 | C29: East | D29: RJ | E29: Neha | F29: Monitor | G29: =INDEX(Lookup_Tables!$B$1:$B$7,MATCH(Cleaned_Data!F29,Lookup_Tables!$A$1:$A$7,0)) -> Electronics | H29: Electronics | I29: 4 | J29: 34893 | K29: 0.1 | L29: =IF(ISBLANK(K29),0,K29) -> 0.1 | N29: =I29*J29 -> 139572 | O29: =N29-(N29*L29) -> 125614.8 | P29: =I29*IFERROR(_xlfn.XLOOKUP(F29,Lookup_Tables!Product,Cost),0) -> 11552 | Q29: =O29-P29 -> 114062.8 | R29: =Q29/O29 -> 0.90803631
A30: ORD0029 | B30: 45315 | C30: South | D30: DL | E30: Amit | F30: Chair | G30: =INDEX(Lookup_Tables!$B$1:$B$7,MATCH(Cleaned_Data!F30,Lookup_Tables!$A$1:$A$7,0)) -> Furniture | H30: Furniture | I30: 9 | J30: 26283 | L30: =IF(ISBLANK(K30),0,K30) -> 0 | N30: =I30*J30 -> 236547 | O30: =N30-(N30*L30) -> 236547 | P30: =I30*IFERROR(_xlfn.XLOOKUP(F30,Lookup_Tables!Product,Cost),0) -> 119439 | Q30: =O30-P30 -> 117108 | R30: =Q30/O30 -> 0.49507286
A31: ORD0030 | B31: 45544 | C31: South | D31: TN | E31: Amit | F31: Laptop | G31: =INDEX(Lookup_Tables!$B$1:$B$7,MATCH(Cleaned_Data!F31,Lookup_Tables!$A$1:$A$7,0)) -> Electronics | H31: Electronics | I31: 2 | J31: 26513 | K31: 0.1 | L31: =IF(ISBLANK(K31),0,K31) -> 0.1 | N31: =I31*J31 -> 53026 | O31: =N31-(N31*L31) -> 47723.4 | P31: =I31*IFERROR(_xlfn.XLOOKUP(F31,Lookup_Tables!Product,Cost),0) -> 38530 | Q31: =O31-P31 -> 9193.4 | R31: =Q31/O31 -> 0.19263925
A32: ORD0031 | B32: 45529 | C32: North | D32: GJ | E32: Amit | F32: Laptop | G32: =INDEX(Lookup_Tables!$B$1:$B$7,MATCH(Cleaned_Data!F32,Lookup_Tables!$A$1:$A$7,0)) -> Electronics | H32: Electronics | I32: 9 | J32: 49552 | K32: 0.1 | L32: =IF(ISBLANK(K32),0,K32) -> 0.1 | M32: 22087 | N32: =I32*J32 -> 445968 | O32: =N32-(N32*L32) -> 401371.2 | P32: =I32*IFERROR(_xlfn.XLOOKUP(F32,Lookup_Tables!Product,Cost),0) -> 173385 | Q32: =O32-P32 -> 227986.2 | R32: =Q32/O32 -> 0.56801833
A33: ORD0032 | B33: 45479 | C33: North | D33: DL | E33: Karan | F33: Monitor | G33: =INDEX(Lookup_Tables!$B$1:$B$7,MATCH(Cleaned_Data!F33,Lookup_Tables!$A$1:$A$7,0)) -> Electronics | H33: Electronics | I33: 6 | J33: 26441 | L33: =IF(ISBLANK(K33),0,K33) -> 0 | M33: 21986 | N33: =I33*J33 -> 158646 | O33: =N33-(N33*L33) -> 158646 | P33: =I33*IFERROR(_xlfn.XLOOKUP(F33,Lookup_Tables!Product,Cost),0) -> 17328 | Q33: =O33-P33 -> 141318 | R33: =Q33/O33 -> 0.89077569
A34: ORD0033 | B34: 45561 | C34: South | D34: RJ | E34: Rahul | F34: Printer | G34: =INDEX(Lookup_Tables!$B$1:$B$7,MATCH(Cleaned_Data!F34,Lookup_Tables!$A$1:$A$7,0)) -> Electronics | H34: Electronics | I34: 9 | J34: 30588 | K34: 0.1 | L34: =IF(ISBLANK(K34),0,K34) -> 0.1 | M34: 22011 | N34: =I34*J34 -> 275292 | O34: =N34-(N34*L34) -> 247762.8 | P34: =I34*IFERROR(_xlfn.XLOOKUP(F34,Lookup_Tables!Product,Cost),0) -> 66456 | Q34: =O34-P34 -> 181306.8 | R34: =Q34/O34 -> 0.73177571
A35: ORD0034 | B35: 45336 | C35: West | D35: TN | E35: Rahul | F35: Monitor | G35: =INDEX(Lookup_Tables!$B$1:$B$7,MATCH(Cleaned_Data!F35,Lookup_Tables!$A$1:$A$7,0)) -> Electronics | H35: Electronics | I35: 9 | J35: 27695 | L35: =IF(ISBLANK(K35),0,K35) -> 0 | N35: =I35*J35 -> 249255 | O35: =N35-(N35*L35) -> 249255 | P35: =I35*IFERROR(_xlfn.XLOOKUP(F35,Lookup_Tables!Product,Cost),0) -> 25992 | Q35: =O35-P35 -> 223263 | R35: =Q35/O35 -> 0.89572125
A36: ORD0035 | B36: 45642 | C36: West | D36: MH | E36: Karan | F36: Printer | G36: =INDEX(Lookup_Tables!$B$1:$B$7,MATCH(Cleaned_Data!F36,Lookup_Tables!$A$1:$A$7,0)) -> Electronics | H36: Electronics | I36: 2 | J36: 10738 | K36: 0 | L36: =IF(ISBLANK(K36),0,K36) -> 0 | M36: 5576 | N36: =I36*J36 -> 21476 | O36: =N36-(N36*L36) -> 21476 | P36: =I36*IFERROR(_xlfn.XLOOKUP(F36,Lookup_Tables!Product,Cost),0) -> 14768 | Q36: =O36-P36 -> 6708 | R36: =Q36/O36 -> 0.31234867
A37: ORD0036 | B37: 45336 | C37: West | D37: MH | E37: Rahul | F37: Monitor | G37: =INDEX(Lookup_Tables!$B$1:$B$7,MATCH(Cleaned_Data!F37,Lookup_Tables!$A$1:$A$7,0)) -> Electronics | H37: Electronics | I37: 6 | J37: 7619 | L37: =IF(ISBLANK(K37),0,K37) -> 0 | M37: 13277 | N37: =I37*J37 -> 45714 | O37: =N37-(N37*L37) -> 45714 | P37: =I37*IFERROR(_xlfn.XLOOKUP(F37,Lookup_Tables!Product,Cost),0) -> 17328 | Q37: =O37-P37 -> 28386 | R37: =Q37/O37 -> 0.62094763
A38: ORD0037 | B38: 45346 | C38: West | D38: GJ | E38: Neha | F38: Laptop | G38: =INDEX(Lookup_Tables!$B$1:$B$7,MATCH(Cleaned_Data!F38,Lookup_Tables!$A$1:$A$7,0)) -> Electronics | H38: Electronics | I38: 8 | J38: 37570 | L38: =IF(ISBLANK(K38),0,K38) -> 0 | N38: =I38*J38 -> 300560 | O38: =N38-(N38*L38) -> 300560 | P38: =I38*IFERROR(_xlfn.XLOOKUP(F38,Lookup_Tables!Product,Cost),0) -> 154120 | Q38: =O38-P38 -> 146440 | R38: =Q38/O38 -> 0.48722385
A39: ORD0038 | B39: 45560 | C39: East | D39: GJ | E39: Neha | F39: Printer | G39: =INDEX(Lookup_Tables!$B$1:$B$7,MATCH(Cleaned_Data!F39,Lookup_Tables!$A$1:$A$7,0)) -> Electronics | H39: Electronics | I39: 1 | J39: 12074 | K39: 0.1 | L39: =IF(ISBLANK(K39),0,K39) -> 0.1 | N39: =I39*J39 -> 12074 | O39: =N39-(N39*L39) -> 10866.6 | P39: =I39*IFERROR(_xlfn.XLOOKUP(F39,Lookup_Tables!Product,Cost),0) -> 7384 | Q39: =O39-P39 -> 3482.6 | R39: =Q39/O39 -> 0.32048663
A40: ORD0039 | B40: 45397 | C40: South | D40: TN | E40: Priya | F40: Printer | G40: =INDEX(Lookup_Tables!$B$1:$B$7,MATCH(Cleaned_Data!F40,Lookup_Tables!$A$1:$A$7,0)) -> Electronics | H40: Electronics | I40: 1 | J40: 44737 | K40: 0.1 | L40: =IF(ISBLANK(K40),0,K40) -> 0.1 | M40: 24975 | N40: =I40*J40 -> 44737 | O40: =N40-(N40*L40) -> 40263.3 | P40: =I40*IFERROR(_xlfn.XLOOKUP(F40,Lookup_Tables!Product,Cost),0) -> 7384 | Q40: =O40-P40 -> 32879.3 | R40: =Q40/O40 -> 0.81660718
A41: ORD0040 | B41: 45329 | C41: North | D41: DL | E41: Karan | F41: Mouse | G41: =INDEX(Lookup_Tables!$B$1:$B$7,MATCH(Cleaned_Data!F41,Lookup_Tables!$A$1:$A$7,0)) -> Electronics | H41: Electronics | I41: 8 | J41: 19251 | K41: 0.05 | L41: =IF(ISBLANK(K41),0,K41) -> 0.05 | M41: 26894 | N41: =I41*J41 -> 154008 | O41: =N41-(N41*L41) -> 146307.6 | P41: =I41*IFERROR(_xlfn.XLOOKUP(F41,Lookup_Tables!Product,Cost),0) -> 224368 | Q41: =O41-P41 -> -78060.4 | R41: =Q41/O41 -> -0.53353619
A42: ORD0041 | B42: 45591 | C42: South | D42: RJ | E42: Amit | F42: Desk | G42: =INDEX(Lookup_Tables!$B$1:$B$7,MATCH(Cleaned_Data!F42,Lookup_Tables!$A$1:$A$7,0)) -> Furniture | H42: Furniture | I42: 3 | J42: 48694 | K42: 0 | L42: =IF(ISBLANK(K42),0,K42) -> 0 | M42: 6974 | N42: =I42*J42 -> 146082 | O42: =N42-(N42*L42) -> 146082 | P42: =I42*IFERROR(_xlfn.XLOOKUP(F42,Lookup_Tables!Product,Cost),0) -> 39120 | Q42: =O42-P42 -> 106962 | R42: =Q42/O42 -> 0.7322052
A43: ORD0042 | B43: 45620 | C43: North | D43: MH | E43: Karan | F43: Chair | G43: =INDEX(Lookup_Tables!$B$1:$B$7,MATCH(Cleaned_Data!F43,Lookup_Tables!$A$1:$A$7,0)) -> Furniture | H43: Furniture | I43: 1 | J43: 35665 | K43: 0.1 | L43: =IF(ISBLANK(K43),0,K43) -> 0.1 | N43: =I43*J43 -> 35665 | O43: =N43-(N43*L43) -> 32098.5 | P43: =I43*IFERROR(_xlfn.XLOOKUP(F43,Lookup_Tables!Product,Cost),0) -> 13271 | Q43: =O43-P43 -> 18827.5 | R43: =Q43/O43 -> 0.58655389
A44: ORD0043 | B44: 45455 | C44: South | D44: MH | E44: Rahul | F44: Chair | G44: =INDEX(Lookup_Tables!$B$1:$B$7,MATCH(Cleaned_Data!F44,Lookup_Tables!$A$1:$A$7,0)) -> Furniture | H44: Furniture | I44: 1 | J44: 18940 | K44: 0 | L44: =IF(ISBLANK(K44),0,K44) -> 0 | N44: =I44*J44 -> 18940 | O44: =N44-(N44*L44) -> 18940 | P44: =I44*IFERROR(_xlfn.XLOOKUP(F44,Lookup_Tables!Product,Cost),0) -> 13271 | Q44: =O44-P44 -> 5669 | R44: =Q44/O44 -> 0.29931362
A45: ORD0044 | B45: 45349 | C45: West | D45: DL | E45: Amit | F45: Printer | G45: =INDEX(Lookup_Tables!$B$1:$B$7,MATCH(Cleaned_Data!F45,Lookup_Tables!$A$1:$A$7,0)) -> Electronics | H45: Electronics | I45: 3 | J45: 672 | K45: 0.05 | L45: =IF(ISBLANK(K45),0,K45) -> 0.05 | M45: 16590 | N45: =I45*J45 -> 2016 | O45: =N45-(N45*L45) -> 1915.2 | P45: =I45*IFERROR(_xlfn.XLOOKUP(F45,Lookup_Tables!Product,Cost),0) -> 22152 | Q45: =O45-P45 -> -20236.8 | R45: =Q45/O45 -> -10.566416
A46: ORD0045 | B46: 45539 | C46: North | D46: TN | E46: Amit | F46: Chair | G46: =INDEX(Lookup_Tables!$B$1:$B$7,MATCH(Cleaned_Data!F46,Lookup_Tables!$A$1:$A$7,0)) -> Furniture | H46: Furniture | I46: 1 | J46: 18649 | K46: 0.1 | L46: =IF(ISBLANK(K46),0,K46) -> 0.1 | M46: 9880 | N46: =I46*J46 -> 18649 | O46: =N46-(N46*L46) -> 16784.1 | P46: =I46*IFERROR(_xlfn.XLOOKUP(F46,Lookup_Tables!Product,Cost),0) -> 13271 | Q46: =O46-P46 -> 3513.1 | R46: =Q46/O46 -> 0.20931119
A47: ORD0046 | B47: 45428 | C47: West | D47: KA | E47: Rahul | F47: Chair | G47: =INDEX(Lookup_Tables!$B$1:$B$7,MATCH(Cleaned_Data!F47,Lookup_Tables!$A$1:$A$7,0)) -> Furniture | H47: Furniture | I47: 4 | J47: 12994 | L47: =IF(ISBLANK(K47),0,K47) -> 0 | M47: 969 | N47: =I47*J47 -> 51976 | O47: =N47-(N47*L47) -> 51976 | P47: =I47*IFERROR(_xlfn.XLOOKUP(F47,Lookup_Tables!Product,Cost),0) -> 53084 | Q47: =O47-P47 -> -1108 | R47: =Q47/O47 -> -0.021317531
A48: ORD0047 | B48: 45432 | C48: South | D48: KA | E48: Priya | F48: Chair | G48: =INDEX(Lookup_Tables!$B$1:$B$7,MATCH(Cleaned_Data!F48,Lookup_Tables!$A$1:$A$7,0)) -> Furniture | H48: Furniture | I48: 8 | J48: 9668 | K48: 0.1 | L48: =IF(ISBLANK(K48),0,K48) -> 0.1 | N48: =I48*J48 -> 77344 | O48: =N48-(N48*L48) -> 69609.6 | P48: =I48*IFERROR(_xlfn.XLOOKUP(F48,Lookup_Tables!Product,Cost),0) -> 106168 | Q48: =O48-P48 -> -36558.4 | R48: =Q48/O48 -> -0.52519193
A49: ORD0048 | B49: 45518 | C49: North | D49: RJ | E49: Priya | F49: Monitor | G49: =INDEX(Lookup_Tables!$B$1:$B$7,MATCH(Cleaned_Data!F49,Lookup_Tables!$A$1:$A$7,0)) -> Electronics | H49: Electronics | I49: 6 | J49: 38361 | K49: 0 | L49: =IF(ISBLANK(K49),0,K49) -> 0 | N49: =I49*J49 -> 230166 | O49: =N49-(N49*L49) -> 230166 | P49: =I49*IFERROR(_xlfn.XLOOKUP(F49,Lookup_Tables!Product,Cost),0) -> 17328 | Q49: =O49-P49 -> 212838 | R49: =Q49/O49 -> 0.92471521
A50: ORD0049 | B50: 45454 | C50: East | D50: DL | E50: Rahul | F50: Desk | G50: =INDEX(Lookup_Tables!$B$1:$B$7,MATCH(Cleaned_Data!F50,Lookup_Tables!$A$1:$A$7,0)) -> Furniture | H50: Furniture | I50: 4 | J50: 2202 | K50: 0.05 | L50: =IF(ISBLANK(K50),0,K50) -> 0.05 | M50: 25372 | N50: =I50*J50 -> 8808 | O50: =N50-(N50*L50) -> 8367.6 | P50: =I50*IFERROR(_xlfn.XLOOKUP(F50,Lookup_Tables!Product,Cost),0) -> 52160 | Q50: =O50-P50 -> -43792.4 | R50: =Q50/O50 -> -5.2335676
A51: ORD0050 | B51: 45639 | C51: West | D51: TN | E51: Neha | F51: Mouse | G51: =INDEX(Lookup_Tables!$B$1:$B$7,MATCH(Cleaned_Data!F51,Lookup_Tables!$A$1:$A$7,0)) -> Electronics | H51: Electronics | I51: 7 | J51: 43713 | K51: 0.1 | L51: =IF(ISBLANK(K51),0,K51) -> 0.1 | N51: =I51*J51 -> 305991 | O51: =N51-(N51*L51) -> 275391.9 | P51: =I51*IFERROR(_xlfn.XLOOKUP(F51,Lookup_Tables!Product,Cost),0) -> 196322 | Q51: =O51-P51 -> 79069.9 | R51: =Q51/O51 -> 0.28711774
A52: ORD0051 | B52: 45399 | C52: West | D52: DL | E52: Priya | F52: Laptop | G52: =INDEX(Lookup_Tables!$B$1:$B$7,MATCH(Cleaned_Data!F52,Lookup_Tables!$A$1:$A$7,0)) -> Electronics | H52: Electronics | I52: 8 | J52: 1172 | L52: =IF(ISBLANK(K52),0,K52) -> 0 | N52: =I52*J52 -> 9376 | O52: =N52-(N52*L52) -> 9376 | P52: =I52*IFERROR(_xlfn.XLOOKUP(F52,Lookup_Tables!Product,Cost),0) -> 154120 | Q52: =O52-P52 -> -144744 | R52: =Q52/O52 -> -15.437713
A53: ORD0052 | B53: 45568 | C53: East | D53: DL | E53: Rahul | F53: Monitor | G53: =INDEX(Lookup_Tables!$B$1:$B$7,MATCH(Cleaned_Data!F53,Lookup_Tables!$A$1:$A$7,0)) -> Electronics | H53: Electronics | I53: 2 | J53: 28932 | L53: =IF(ISBLANK(K53),0,K53) -> 0 | M53: 19839 | N53: =I53*J53 -> 57864 | O53: =N53-(N53*L53) -> 57864 | P53: =I53*IFERROR(_xlfn.XLOOKUP(F53,Lookup_Tables!Product,Cost),0) -> 5776 | Q53: =O53-P53 -> 52088 | R53: =Q53/O53 -> 0.90017973
A54: ORD0053 | B54: 45379 | C54: South | D54: GJ | E54: Priya | F54: Printer | G54: =INDEX(Lookup_Tables!$B$1:$B$7,MATCH(Cleaned_Data!F54,Lookup_Tables!$A$1:$A$7,0)) -> Electronics | H54: Electronics | I54: 9 | J54: 12134 | K54: 0 | L54: =IF(ISBLANK(K54),0,K54) -> 0 | N54: =I54*J54 -> 109206 | O54: =N54-(N54*L54) -> 109206 | P54: =I54*IFERROR(_xlfn.XLOOKUP(F54,Lookup_Tables!Product,Cost),0) -> 66456 | Q54: =O54-P54 -> 42750 | R54: =Q54/O54 -> 0.39146201
A55: ORD0054 | B55: 45619 | C55: South | D55: RJ | E55: Karan | F55: Chair | G55: =INDEX(Lookup_Tables!$B$1:$B$7,MATCH(Cleaned_Data!F55,Lookup_Tables!$A$1:$A$7,0)) -> Furniture | H55: Furniture | I55: 6 | J55: 28535 | K55: 0.05 | L55: =IF(ISBLANK(K55),0,K55) -> 0.05 | N55: =I55*J55 -> 171210 | O55: =N55-(N55*L55) -> 162649.5 | P55: =I55*IFERROR(_xlfn.XLOOKUP(F55,Lookup_Tables!Product,Cost),0) -> 79626 | Q55: =O55-P55 -> 83023.5 | R55: =Q55/O55 -> 0.51044424
A56: ORD0055 | B56: 45367 | C56: East | D56: KA | E56: Neha | F56: Printer | G56: =INDEX(Lookup_Tables!$B$1:$B$7,MATCH(Cleaned_Data!F56,Lookup_Tables!$A$1:$A$7,0)) -> Electronics | H56: Electronics | I56: 10 | J56: 18292 | L56: =IF(ISBLANK(K56),0,K56) -> 0 | N56: =I56*J56 -> 182920 | O56: =N56-(N56*L56) -> 182920 | P56: =I56*IFERROR(_xlfn.XLOOKUP(F56,Lookup_Tables!Product,Cost),0) -> 73840 | Q56: =O56-P56 -> 109080 | R56: =Q56/O56 -> 0.59632626
A57: ORD0056 | B57: 45453 | C57: East | D57: GJ | E57: Amit | F57: Monitor | G57: =INDEX(Lookup_Tables!$B$1:$B$7,MATCH(Cleaned_Data!F57,Lookup_Tables!$A$1:$A$7,0)) -> Electronics | H57: Electronics | I57: 1 | J57: 21732 | K57: 0.1 | L57: =IF(ISBLANK(K57),0,K57) -> 0.1 | M57: 3127 | N57: =I57*J57 -> 21732 | O57: =N57-(N57*L57) -> 19558.8 | P57: =I57*IFERROR(_xlfn.XLOOKUP(F57,Lookup_Tables!Product,Cost),0) -> 2888 | Q57: =O57-P57 -> 16670.8 | R57: =Q57/O57 -> 0.85234268
A58: ORD0057 | B58: 45612 | C58: North | D58: TN | E58: Priya | F58: Printer | G58: =INDEX(Lookup_Tables!$B$1:$B$7,MATCH(Cleaned_Data!F58,Lookup_Tables!$A$1:$A$7,0)) -> Electronics | H58: Electronics | I58: 9 | J58: 33284 | K58: 0.05 | L58: =IF(ISBLANK(K58),0,K58) -> 0.05 | N58: =I58*J58 -> 299556 | O58: =N58-(N58*L58) -> 284578.2 | P58: =I58*IFERROR(_xlfn.XLOOKUP(F58,Lookup_Tables!Product,Cost),0) -> 66456 | Q58: =O58-P58 -> 218122.2 | R58: =Q58/O58 -> 0.76647544
A59: ORD0058 | B59: 45589 | C59: North | D59: DL | E59: Neha | F59: Laptop | G59: =INDEX(Lookup_Tables!$B$1:$B$7,MATCH(Cleaned_Data!F59,Lookup_Tables!$A$1:$A$7,0)) -> Electronics | H59: Electronics | I59: 7 | J59: 10389 | L59: =IF(ISBLANK(K59),0,K59) -> 0 | M59: 22159 | N59: =I59*J59 -> 72723 | O59: =N59-(N59*L59) -> 72723 | P59: =I59*IFERROR(_xlfn.XLOOKUP(F59,Lookup_Tables!Product,Cost),0) -> 134855 | Q59: =O59-P59 -> -62132 | R59: =Q59/O59 -> -0.85436519
A60: ORD0059 | B60: 45326 | C60: East | D60: RJ | E60: Amit | F60: Chair | G60: =INDEX(Lookup_Tables!$B$1:$B$7,MATCH(Cleaned_Data!F60,Lookup_Tables!$A$1:$A$7,0)) -> Furniture | H60: Furniture | I60: 9 | J60: 5625 | L60: =IF(ISBLANK(K60),0,K60) -> 0 | M60: 9293 | N60: =I60*J60 -> 50625 | O60: =N60-(N60*L60) -> 50625 | P60: =I60*IFERROR(_xlfn.XLOOKUP(F60,Lookup_Tables!Product,Cost),0) -> 119439 | Q60: =O60-P60 -> -68814 | R60: =Q60/O60 -> -1.3592889
A61: ORD0060 | B61: 45606 | C61: South | D61: DL | E61: Rahul | F61: Mouse | G61: =INDEX(Lookup_Tables!$B$1:$B$7,MATCH(Cleaned_Data!F61,Lookup_Tables!$A$1:$A$7,0)) -> Electronics | H61: Electronics | I61: 7 | J61: 40540 | K61: 0 | L61: =IF(ISBLANK(K61),0,K61) -> 0 | N61: =I61*J61 -> 283780 | O61: =N61-(N61*L61) -> 283780 | P61: =I61*IFERROR(_xlfn.XLOOKUP(F61,Lookup_Tables!Product,Cost),0) -> 196322 | Q61: =O61-P61 -> 87458 | R61: =Q61/O61 -> 0.30818944
A62: ORD0061 | B62: 45596 | C62: West | D62: RJ | E62: Amit | F62: Desk | G62: =INDEX(Lookup_Tables!$B$1:$B$7,MATCH(Cleaned_Data!F62,Lookup_Tables!$A$1:$A$7,0)) -> Furniture | H62: Furniture | I62: 2 | J62: 1279 | K62: 0.05 | L62: =IF(ISBLANK(K62),0,K62) -> 0.05 | M62: 7957 | N62: =I62*J62 -> 2558 | O62: =N62-(N62*L62) -> 2430.1 | P62: =I62*IFERROR(_xlfn.XLOOKUP(F62,Lookup_Tables!Product,Cost),0) -> 26080 | Q62: =O62-P62 -> -23649.9 | R62: =Q62/O62 -> -9.7320686
A63: ORD0062 | B63: 45475 | C63: North | D63: RJ | E63: Amit | F63: Mouse | G63: =INDEX(Lookup_Tables!$B$1:$B$7,MATCH(Cleaned_Data!F63,Lookup_Tables!$A$1:$A$7,0)) -> Electronics | H63: Electronics | I63: 7 | J63: 16631 | K63: 0.1 | L63: =IF(ISBLANK(K63),0,K63) -> 0.1 | M63: 4214 | N63: =I63*J63 -> 116417 | O63: =N63-(N63*L63) -> 104775.3 | P63: =I63*IFERROR(_xlfn.XLOOKUP(F63,Lookup_Tables!Product,Cost),0) -> 196322 | Q63: =O63-P63 -> -91546.7 | R63: =Q63/O63 -> -0.87374314
A64: ORD0063 | B64: 45558 | C64: North | D64: RJ | E64: Rahul | F64: Chair | G64: =INDEX(Lookup_Tables!$B$1:$B$7,MATCH(Cleaned_Data!F64,Lookup_Tables!$A$1:$A$7,0)) -> Furniture | H64: Furniture | I64: 7 | J64: 32756 | K64: 0 | L64: =IF(ISBLANK(K64),0,K64) -> 0 | M64: 16465 | N64: =I64*J64 -> 229292 | O64: =N64-(N64*L64) -> 229292 | P64: =I64*IFERROR(_xlfn.XLOOKUP(F64,Lookup_Tables!Product,Cost),0) -> 92897 | Q64: =O64-P64 -> 136395 | R64: =Q64/O64 -> 0.59485285
A65: ORD0064 | B65: 45562 | C65: North | D65: MH | E65: Karan | F65: Printer | G65: =INDEX(Lookup_Tables!$B$1:$B$7,MATCH(Cleaned_Data!F65,Lookup_Tables!$A$1:$A$7,0)) -> Electronics | H65: Electronics | I65: 7 | J65: 22550 | K65: 0.1 | L65: =IF(ISBLANK(K65),0,K65) -> 0.1 | N65: =I65*J65 -> 157850 | O65: =N65-(N65*L65) -> 142065 | P65: =I65*IFERROR(_xlfn.XLOOKUP(F65,Lookup_Tables!Product,Cost),0) -> 51688 | Q65: =O65-P65 -> 90377 | R65: =Q65/O65 -> 0.63616654
A66: ORD0065 | B66: 45636 | C66: North | D66: RJ | E66: Amit | F66: Desk | G66: =INDEX(Lookup_Tables!$B$1:$B$7,MATCH(Cleaned_Data!F66,Lookup_Tables!$A$1:$A$7,0)) -> Furniture | H66: Furniture | I66: 8 | J66: 22339 | K66: 0 | L66: =IF(ISBLANK(K66),0,K66) -> 0 | M66: 2121 | N66: =I66*J66 -> 178712 | O66: =N66-(N66*L66) -> 178712 | P66: =I66*IFERROR(_xlfn.XLOOKUP(F66,Lookup_Tables!Product,Cost),0) -> 104320 | Q66: =O66-P66 -> 74392 | R66: =Q66/O66 -> 0.41626751
A67: ORD0066 | B67: 45507 | C67: West | D67: KA | E67: Amit | F67: Laptop | G67: =INDEX(Lookup_Tables!$B$1:$B$7,MATCH(Cleaned_Data!F67,Lookup_Tables!$A$1:$A$7,0)) -> Electronics | H67: Electronics | I67: 2 | J67: 46159 | K67: 0.05 | L67: =IF(ISBLANK(K67),0,K67) -> 0.05 | N67: =I67*J67 -> 92318 | O67: =N67-(N67*L67) -> 87702.1 | P67: =I67*IFERROR(_xlfn.XLOOKUP(F67,Lookup_Tables!Product,Cost),0) -> 38530 | Q67: =O67-P67 -> 49172.1 | R67: =Q67/O67 -> 0.56067187
A68: ORD0067 | B68: 45328 | C68: North | D68: DL | E68: Karan | F68: Desk | G68: =INDEX(Lookup_Tables!$B$1:$B$7,MATCH(Cleaned_Data!F68,Lookup_Tables!$A$1:$A$7,0)) -> Furniture | H68: Furniture | I68: 6 | J68: 22125 | K68: 0 | L68: =IF(ISBLANK(K68),0,K68) -> 0 | M68: 29712 | N68: =I68*J68 -> 132750 | O68: =N68-(N68*L68) -> 132750 | P68: =I68*IFERROR(_xlfn.XLOOKUP(F68,Lookup_Tables!Product,Cost),0) -> 78240 | Q68: =O68-P68 -> 54510 | R68: =Q68/O68 -> 0.41062147
A69: ORD0068 | B69: 45594 | C69: South | D69: GJ | E69: Karan | F69: Mouse | G69: =INDEX(Lookup_Tables!$B$1:$B$7,MATCH(Cleaned_Data!F69,Lookup_Tables!$A$1:$A$7,0)) -> Electronics | H69: Electronics | I69: 6 | J69: 41323 | L69: =IF(ISBLANK(K69),0,K69) -> 0 | M69: 17325 | N69: =I69*J69 -> 247938 | O69: =N69-(N69*L69) -> 247938 | P69: =I69*IFERROR(_xlfn.XLOOKUP(F69,Lookup_Tables!Product,Cost),0) -> 168276 | Q69: =O69-P69 -> 79662 | R69: =Q69/O69 -> 0.32129807
A70: ORD0069 | B70: 45300 | C70: West | D70: RJ | E70: Neha | F70: Desk | G70: =INDEX(Lookup_Tables!$B$1:$B$7,MATCH(Cleaned_Data!F70,Lookup_Tables!$A$1:$A$7,0)) -> Furniture | H70: Furniture | I70: 3 | J70: 28541 | K70: 0.1 | L70: =IF(ISBLANK(K70),0,K70) -> 0.1 | M70: 6771 | N70: =I70*J70 -> 85623 | O70: =N70-(N70*L70) -> 77060.7 | P70: =I70*IFERROR(_xlfn.XLOOKUP(F70,Lookup_Tables!Product,Cost),0) -> 39120 | Q70: =O70-P70 -> 37940.7 | R70: =Q70/O70 -> 0.49234824
A71: ORD0070 | B71: 45582 | C71: South | D71: DL | E71: Amit | F71: Chair | G71: =INDEX(Lookup_Tables!$B$1:$B$7,MATCH(Cleaned_Data!F71,Lookup_Tables!$A$1:$A$7,0)) -> Furniture | H71: Furniture | I71: 7 | J71: 16466 | L71: =IF(ISBLANK(K71),0,K71) -> 0 | M71: 22928 | N71: =I71*J71 -> 115262 | O71: =N71-(N71*L71) -> 115262 | P71: =I71*IFERROR(_xlfn.XLOOKUP(F71,Lookup_Tables!Product,Cost),0) -> 92897 | Q71: =O71-P71 -> 22365 | R71: =Q71/O71 -> 0.1940362
A72: ORD0071 | B72: 45310 | C72: East | D72: DL | E72: Rahul | F72: Desk | G72: =INDEX(Lookup_Tables!$B$1:$B$7,MATCH(Cleaned_Data!F72,Lookup_Tables!$A$1:$A$7,0)) -> Furniture | H72: Furniture | I72: 2 | J72: 12316 | L72: =IF(ISBLANK(K72),0,K72) -> 0 | N72: =I72*J72 -> 24632 | O72: =N72-(N72*L72) -> 24632 | P72: =I72*IFERROR(_xlfn.XLOOKUP(F72,Lookup_Tables!Product,Cost),0) -> 26080 | Q72: =O72-P72 -> -1448 | R72: =Q72/O72 -> -0.05878532
A73: ORD0072 | B73: 45491 | C73: West | D73: MH | E73: Amit | F73: Desk | G73: =INDEX(Lookup_Tables!$B$1:$B$7,MATCH(Cleaned_Data!F73,Lookup_Tables!$A$1:$A$7,0)) -> Furniture | H73: Furniture | I73: 10 | J73: 34687 | L73: =IF(ISBLANK(K73),0,K73) -> 0 | M73: 10859 | N73: =I73*J73 -> 346870 | O73: =N73-(N73*L73) -> 346870 | P73: =I73*IFERROR(_xlfn.XLOOKUP(F73,Lookup_Tables!Product,Cost),0) -> 130400 | Q73: =O73-P73 -> 216470 | R73: =Q73/O73 -> 0.62406665
A74: ORD0073 | B74: 45626 | C74: East | D74: KA | E74: Amit | F74: Desk | G74: =INDEX(Lookup_Tables!$B$1:$B$7,MATCH(Cleaned_Data!F74,Lookup_Tables!$A$1:$A$7,0)) -> Furniture | H74: Furniture | I74: 4 | J74: 32319 | K74: 0.05 | L74: =IF(ISBLANK(K74),0,K74) -> 0.05 | M74: 20290 | N74: =I74*J74 -> 129276 | O74: =N74-(N74*L74) -> 122812.2 | P74: =I74*IFERROR(_xlfn.XLOOKUP(F74,Lookup_Tables!Product,Cost),0) -> 52160 | Q74: =O74-P74 -> 70652.2 | R74: =Q74/O74 -> 0.57528649
A75: ORD0074 | B75: 45323 | C75: North | D75: KA | E75: Priya | F75: Monitor | G75: =INDEX(Lookup_Tables!$B$1:$B$7,MATCH(Cleaned_Data!F75,Lookup_Tables!$A$1:$A$7,0)) -> Electronics | H75: Electronics | I75: 1 | J75: 1976 | K75: 0.05 | L75: =IF(ISBLANK(K75),0,K75) -> 0.05 | M75: 5597 | N75: =I75*J75 -> 1976 | O75: =N75-(N75*L75) -> 1877.2 | P75: =I75*IFERROR(_xlfn.XLOOKUP(F75,Lookup_Tables!Product,Cost),0) -> 2888 | Q75: =O75-P75 -> -1010.8 | R75: =Q75/O75 -> -0.53846154
A76: ORD0075 | B76: 45336 | C76: South | D76: RJ | E76: Amit | F76: Printer | G76: =INDEX(Lookup_Tables!$B$1:$B$7,MATCH(Cleaned_Data!F76,Lookup_Tables!$A$1:$A$7,0)) -> Electronics | H76: Electronics | I76: 4 | J76: 27237 | K76: 0 | L76: =IF(ISBLANK(K76),0,K76) -> 0 | M76: 17550 | N76: =I76*J76 -> 108948 | O76: =N76-(N76*L76) -> 108948 | P76: =I76*IFERROR(_xlfn.XLOOKUP(F76,Lookup_Tables!Product,Cost),0) -> 29536 | Q76: =O76-P76 -> 79412 | R76: =Q76/O76 -> 0.72889819
A77: ORD0076 | B77: 45424 | C77: South | D77: DL | E77: Amit | F77: Mouse | G77: =INDEX(Lookup_Tables!$B$1:$B$7,MATCH(Cleaned_Data!F77,Lookup_Tables!$A$1:$A$7,0)) -> Electronics | H77: Electronics | I77: 8 | J77: 36429 | K77: 0.05 | L77: =IF(ISBLANK(K77),0,K77) -> 0.05 | M77: 15686 | N77: =I77*J77 -> 291432 | O77: =N77-(N77*L77) -> 276860.4 | P77: =I77*IFERROR(_xlfn.XLOOKUP(F77,Lookup_Tables!Product,Cost),0) -> 224368 | Q77: =O77-P77 -> 52492.4 | R77: =Q77/O77 -> 0.1895988
A78: ORD0077 | B78: 45579 | C78: East | D78: DL | E78: Rahul | F78: Chair | G78: =INDEX(Lookup_Tables!$B$1:$B$7,MATCH(Cleaned_Data!F78,Lookup_Tables!$A$1:$A$7,0)) -> Furniture | H78: Furniture | I78: 7 | J78: 30010 | K78: 0 | L78: =IF(ISBLANK(K78),0,K78) -> 0 | M78: 6503 | N78: =I78*J78 -> 210070 | O78: =N78-(N78*L78) -> 210070 | P78: =I78*IFERROR(_xlfn.XLOOKUP(F78,Lookup_Tables!Product,Cost),0) -> 92897 | Q78: =O78-P78 -> 117173 | R78: =Q78/O78 -> 0.55778074
A79: ORD0078 | B79: 45351 | C79: East | D79: GJ | E79: Neha | F79: Laptop | G79: =INDEX(Lookup_Tables!$B$1:$B$7,MATCH(Cleaned_Data!F79,Lookup_Tables!$A$1:$A$7,0)) -> Electronics | H79: Electronics | I79: 2 | J79: 15440 | K79: 0.1 | L79: =IF(ISBLANK(K79),0,K79) -> 0.1 | M79: 18884 | N79: =I79*J79 -> 30880 | O79: =N79-(N79*L79) -> 27792 | P79: =I79*IFERROR(_xlfn.XLOOKUP(F79,Lookup_Tables!Product,Cost),0) -> 38530 | Q79: =O79-P79 -> -10738 | R79: =Q79/O79 -> -0.38637018
A80: ORD0079 | B80: 45339 | C80: South | D80: KA | E80: Neha | F80: Mouse | G80: =INDEX(Lookup_Tables!$B$1:$B$7,MATCH(Cleaned_Data!F80,Lookup_Tables!$A$1:$A$7,0)) -> Electronics | H80: Electronics | I80: 1 | J80: 26526 | K80: 0.05 | L80: =IF(ISBLANK(K80),0,K80) -> 0.05 | N80: =I80*J80 -> 26526 | O80: =N80-(N80*L80) -> 25199.7 | P80: =I80*IFERROR(_xlfn.XLOOKUP(F80,Lookup_Tables!Product,Cost),0) -> 28046 | Q80: =O80-P80 -> -2846.3 | R80: =Q80/O80 -> -0.11294976
A81: ORD0080 | B81: 45303 | C81: South | D81: DL | E81: Priya | F81: Mouse | G81: =INDEX(Lookup_Tables!$B$1:$B$7,MATCH(Cleaned_Data!F81,Lookup_Tables!$A$1:$A$7,0)) -> Electronics | H81: Electronics | I81: 10 | J81: 41127 | K81: 0.05 | L81: =IF(ISBLANK(K81),0,K81) -> 0.05 | M81: 2039 | N81: =I81*J81 -> 411270 | O81: =N81-(N81*L81) -> 390706.5 | P81: =I81*IFERROR(_xlfn.XLOOKUP(F81,Lookup_Tables!Product,Cost),0) -> 280460 | Q81: =O81-P81 -> 110246.5 | R81: =Q81/O81 -> 0.28217217
A82: ORD0081 | B82: 45596 | C82: North | D82: MH | E82: Neha | F82: Mouse | G82: =INDEX(Lookup_Tables!$B$1:$B$7,MATCH(Cleaned_Data!F82,Lookup_Tables!$A$1:$A$7,0)) -> Electronics | H82: Electronics | I82: 7 | J82: 5533 | K82: 0.05 | L82: =IF(ISBLANK(K82),0,K82) -> 0.05 | N82: =I82*J82 -> 38731 | O82: =N82-(N82*L82) -> 36794.45 | P82: =I82*IFERROR(_xlfn.XLOOKUP(F82,Lookup_Tables!Product,Cost),0) -> 196322 | Q82: =O82-P82 -> -159527.55 | R82: =Q82/O82 -> -4.3356417
A83: ORD0082 | B83: 45310 | C83: North | D83: MH | E83: Amit | F83: Chair | G83: =INDEX(Lookup_Tables!$B$1:$B$7,MATCH(Cleaned_Data!F83,Lookup_Tables!$A$1:$A$7,0)) -> Furniture | H83: Furniture | I83: 1 | J83: 4265 | K83: 0.1 | L83: =IF(ISBLANK(K83),0,K83) -> 0.1 | N83: =I83*J83 -> 4265 | O83: =N83-(N83*L83) -> 3838.5 | P83: =I83*IFERROR(_xlfn.XLOOKUP(F83,Lookup_Tables!Product,Cost),0) -> 13271 | Q83: =O83-P83 -> -9432.5 | R83: =Q83/O83 -> -2.4573401
A84: ORD0083 | B84: 45495 | C84: East | D84: KA | E84: Karan | F84: Monitor | G84: =INDEX(Lookup_Tables!$B$1:$B$7,MATCH(Cleaned_Data!F84,Lookup_Tables!$A$1:$A$7,0)) -> Electronics | H84: Electronics | I84: 1 | J84: 40542 | L84: =IF(ISBLANK(K84),0,K84) -> 0 | N84: =I84*J84 -> 40542 | O84: =N84-(N84*L84) -> 40542 | P84: =I84*IFERROR(_xlfn.XLOOKUP(F84,Lookup_Tables!Product,Cost),0) -> 2888 | Q84: =O84-P84 -> 37654 | R84: =Q84/O84 -> 0.92876523
A85: ORD0084 | B85: 45421 | C85: South | D85: KA | E85: Neha | F85: Printer | G85: =INDEX(Lookup_Tables!$B$1:$B$7,MATCH(Cleaned_Data!F85,Lookup_Tables!$A$1:$A$7,0)) -> Electronics | H85: Electronics | I85: 1 | J85: 10295 | L85: =IF(ISBLANK(K85),0,K85) -> 0 | M85: 9606 | N85: =I85*J85 -> 10295 | O85: =N85-(N85*L85) -> 10295 | P85: =I85*IFERROR(_xlfn.XLOOKUP(F85,Lookup_Tables!Product,Cost),0) -> 7384 | Q85: =O85-P85 -> 2911 | R85: =Q85/O85 -> 0.28275862
A86: ORD0085 | B86: 45614 | C86: East | D86: GJ | E86: Karan | F86: Mouse | G86: =INDEX(Lookup_Tables!$B$1:$B$7,MATCH(Cleaned_Data!F86,Lookup_Tables!$A$1:$A$7,0)) -> Electronics | H86: Electronics | I86: 10 | J86: 43135 | L86: =IF(ISBLANK(K86),0,K86) -> 0 | N86: =I86*J86 -> 431350 | O86: =N86-(N86*L86) -> 431350 | P86: =I86*IFERROR(_xlfn.XLOOKUP(F86,Lookup_Tables!Product,Cost),0) -> 280460 | Q86: =O86-P86 -> 150890 | R86: =Q86/O86 -> 0.34980874
A87: ORD0086 | B87: 45428 | C87: East | D87: RJ | E87: Priya | F87: Printer | G87: =INDEX(Lookup_Tables!$B$1:$B$7,MATCH(Cleaned_Data!F87,Lookup_Tables!$A$1:$A$7,0)) -> Electronics | H87: Electronics | I87: 3 | J87: 22790 | K87: 0.05 | L87: =IF(ISBLANK(K87),0,K87) -> 0.05 | N87: =I87*J87 -> 68370 | O87: =N87-(N87*L87) -> 64951.5 | P87: =I87*IFERROR(_xlfn.XLOOKUP(F87,Lookup_Tables!Product,Cost),0) -> 22152 | Q87: =O87-P87 -> 42799.5 | R87: =Q87/O87 -> 0.65894552
A88: ORD0087 | B88: 45311 | C88: West | D88: MH | E88: Neha | F88: Laptop | G88: =INDEX(Lookup_Tables!$B$1:$B$7,MATCH(Cleaned_Data!F88,Lookup_Tables!$A$1:$A$7,0)) -> Electronics | H88: Electronics | I88: 10 | J88: 36203 | K88: 0.05 | L88: =IF(ISBLANK(K88),0,K88) -> 0.05 | M88: 4593 | N88: =I88*J88 -> 362030 | O88: =N88-(N88*L88) -> 343928.5 | P88: =I88*IFERROR(_xlfn.XLOOKUP(F88,Lookup_Tables!Product,Cost),0) -> 192650 | Q88: =O88-P88 -> 151278.5 | R88: =Q88/O88 -> 0.4398545
A89: ORD0088 | B89: 45452 | C89: West | D89: KA | E89: Neha | F89: Chair | G89: =INDEX(Lookup_Tables!$B$1:$B$7,MATCH(Cleaned_Data!F89,Lookup_Tables!$A$1:$A$7,0)) -> Furniture | H89: Furniture | I89: 2 | J89: 29990 | K89: 0 | L89: =IF(ISBLANK(K89),0,K89) -> 0 | N89: =I89*J89 -> 59980 | O89: =N89-(N89*L89) -> 59980 | P89: =I89*IFERROR(_xlfn.XLOOKUP(F89,Lookup_Tables!Product,Cost),0) -> 26542 | Q89: =O89-P89 -> 33438 | R89: =Q89/O89 -> 0.55748583
A90: ORD0089 | B90: 45402 | C90: South | D90: KA | E90: Rahul | F90: Desk | G90: =INDEX(Lookup_Tables!$B$1:$B$7,MATCH(Cleaned_Data!F90,Lookup_Tables!$A$1:$A$7,0)) -> Furniture | H90: Furniture | I90: 2 | J90: 34584 | L90: =IF(ISBLANK(K90),0,K90) -> 0 | N90: =I90*J90 -> 69168 | O90: =N90-(N90*L90) -> 69168 | P90: =I90*IFERROR(_xlfn.XLOOKUP(F90,Lookup_Tables!Product,Cost),0) -> 26080 | Q90: =O90-P90 -> 43088 | R90: =Q90/O90 -> 0.62294703
A91: ORD0090 | B91: 45332 | C91: North | D91: DL | E91: Amit | F91: Desk | G91: =INDEX(Lookup_Tables!$B$1:$B$7,MATCH(Cleaned_Data!F91,Lookup_Tables!$A$1:$A$7,0)) -> Furniture | H91: Furniture | I91: 8 | J91: 6065 | K91: 0.05 | L91: =IF(ISBLANK(K91),0,K91) -> 0.05 | M91: 11003 | N91: =I91*J91 -> 48520 | O91: =N91-(N91*L91) -> 46094 | P91: =I91*IFERROR(_xlfn.XLOOKUP(F91,Lookup_Tables!Product,Cost),0) -> 104320 | Q91: =O91-P91 -> -58226 | R91: =Q91/O91 -> -1.2632013
A92: ORD0091 | B92: 45651 | C92: North | D92: MH | E92: Rahul | F92: Printer | G92: =INDEX(Lookup_Tables!$B$1:$B$7,MATCH(Cleaned_Data!F92,Lookup_Tables!$A$1:$A$7,0)) -> Electronics | H92: Electronics | I92: 9 | J92: 35616 | L92: =IF(ISBLANK(K92),0,K92) -> 0 | M92: 14753 | N92: =I92*J92 -> 320544 | O92: =N92-(N92*L92) -> 320544 | P92: =I92*IFERROR(_xlfn.XLOOKUP(F92,Lookup_Tables!Product,Cost),0) -> 66456 | Q92: =O92-P92 -> 254088 | R92: =Q92/O92 -> 0.79267745
A93: ORD0092 | B93: 45542 | C93: North | D93: GJ | E93: Neha | F93: Monitor | G93: =INDEX(Lookup_Tables!$B$1:$B$7,MATCH(Cleaned_Data!F93,Lookup_Tables!$A$1:$A$7,0)) -> Electronics | H93: Electronics | I93: 7 | J93: 14701 | K93: 0.05 | L93: =IF(ISBLANK(K93),0,K93) -> 0.05 | N93: =I93*J93 -> 102907 | O93: =N93-(N93*L93) -> 97761.65 | P93: =I93*IFERROR(_xlfn.XLOOKUP(F93,Lookup_Tables!Product,Cost),0) -> 20216 | Q93: =O93-P93 -> 77545.65 | R93: =Q93/O93 -> 0.79321135
A94: ORD0093 | B94: 45592 | C94: East | D94: TN | E94: Neha | F94: Printer | G94: =INDEX(Lookup_Tables!$B$1:$B$7,MATCH(Cleaned_Data!F94,Lookup_Tables!$A$1:$A$7,0)) -> Electronics | H94: Electronics | I94: 8 | J94: 11159 | L94: =IF(ISBLANK(K94),0,K94) -> 0 | M94: 959 | N94: =I94*J94 -> 89272 | O94: =N94-(N94*L94) -> 89272 | P94: =I94*IFERROR(_xlfn.XLOOKUP(F94,Lookup_Tables!Product,Cost),0) -> 59072 | Q94: =O94-P94 -> 30200 | R94: =Q94/O94 -> 0.33829196
A95: ORD0094 | B95: 45471 | C95: North | D95: KA | E95: Rahul | F95: Monitor | G95: =INDEX(Lookup_Tables!$B$1:$B$7,MATCH(Cleaned_Data!F95,Lookup_Tables!$A$1:$A$7,0)) -> Electronics | H95: Electronics | I95: 6 | J95: 39961 | K95: 0.1 | L95: =IF(ISBLANK(K95),0,K95) -> 0.1 | M95: 24009 | N95: =I95*J95 -> 239766 | O95: =N95-(N95*L95) -> 215789.4 | P95: =I95*IFERROR(_xlfn.XLOOKUP(F95,Lookup_Tables!Product,Cost),0) -> 17328 | Q95: =O95-P95 -> 198461.4 | R95: =Q95/O95 -> 0.91969948
A96: ORD0095 | B96: 45383 | C96: West | D96: KA | E96: Rahul | F96: Printer | G96: =INDEX(Lookup_Tables!$B$1:$B$7,MATCH(Cleaned_Data!F96,Lookup_Tables!$A$1:$A$7,0)) -> Electronics | H96: Electronics | I96: 9 | J96: 12105 | K96: 0.05 | L96: =IF(ISBLANK(K96),0,K96) -> 0.05 | N96: =I96*J96 -> 108945 | O96: =N96-(N96*L96) -> 103497.75 | P96: =I96*IFERROR(_xlfn.XLOOKUP(F96,Lookup_Tables!Product,Cost),0) -> 66456 | Q96: =O96-P96 -> 37041.75 | R96: =Q96/O96 -> 0.35789908
A97: ORD0096 | B97: 45516 | C97: West | D97: MH | E97: Neha | F97: Chair | G97: =INDEX(Lookup_Tables!$B$1:$B$7,MATCH(Cleaned_Data!F97,Lookup_Tables!$A$1:$A$7,0)) -> Furniture | H97: Furniture | I97: 4 | J97: 18667 | K97: 0.1 | L97: =IF(ISBLANK(K97),0,K97) -> 0.1 | M97: 13662 | N97: =I97*J97 -> 74668 | O97: =N97-(N97*L97) -> 67201.2 | P97: =I97*IFERROR(_xlfn.XLOOKUP(F97,Lookup_Tables!Product,Cost),0) -> 53084 | Q97: =O97-P97 -> 14117.2 | R97: =Q97/O97 -> 0.21007363
A98: ORD0097 | B98: 45390 | C98: North | D98: GJ | E98: Amit | F98: Printer | G98: =INDEX(Lookup_Tables!$B$1:$B$7,MATCH(Cleaned_Data!F98,Lookup_Tables!$A$1:$A$7,0)) -> Electronics | H98: Electronics | I98: 9 | J98: 30848 | K98: 0.1 | L98: =IF(ISBLANK(K98),0,K98) -> 0.1 | M98: 24623 | N98: =I98*J98 -> 277632 | O98: =N98-(N98*L98) -> 249868.8 | P98: =I98*IFERROR(_xlfn.XLOOKUP(F98,Lookup_Tables!Product,Cost),0) -> 66456 | Q98: =O98-P98 -> 183412.8 | R98: =Q98/O98 -> 0.73403642
A99: ORD0098 | B99: 45345 | C99: South | D99: KA | E99: Amit | F99: Laptop | G99: =INDEX(Lookup_Tables!$B$1:$B$7,MATCH(Cleaned_Data!F99,Lookup_Tables!$A$1:$A$7,0)) -> Electronics | H99: Electronics | I99: 9 | J99: 2772 | K99: 0.05 | L99: =IF(ISBLANK(K99),0,K99) -> 0.05 | M99: 969 | N99: =I99*J99 -> 24948 | O99: =N99-(N99*L99) -> 23700.6 | P99: =I99*IFERROR(_xlfn.XLOOKUP(F99,Lookup_Tables!Product,Cost),0) -> 173385 | Q99: =O99-P99 -> -149684.4 | R99: =Q99/O99 -> -6.3156376
A100: ORD0099 | B100: 45366 | C100: North | D100: MH | E100: Karan | F100: Chair | G100: =INDEX(Lookup_Tables!$B$1:$B$7,MATCH(Cleaned_Data!F100,Lookup_Tables!$A$1:$A$7,0)) -> Furniture | H100: Furniture | I100: 9 | J100: 30646 | K100: 0 | L100: =IF(ISBLANK(K100),0,K100) -> 0 | N100: =I100*J100 -> 275814 | O100: =N100-(N100*L100) -> 275814 | P100: =I100*IFERROR(_xlfn.XLOOKUP(F100,Lookup_Tables!Product,Cost),0) -> 119439 | Q100: =O100-P100 -> 156375 | R100: =Q100/O100 -> 0.56695817
...

Sheet Raw_Data
A1: Order ID | B1: Order Date | C1: Region | D1: State | E1: Salesperson | F1: Product | G1: Category | H1: Quantity | I1: Unit Price | J1: Discount | K1: Cost Price
A2: ORD0001 | B2: 45503 | C2: East | D2: MH | E2: Rahul | F2: Chair | G2: Furniture | H2: 8 | I2: 25761 | J2: 0.05 | K2: 29955
A3: ORD0002 | B3: 45527 | C3: West | D3: RJ | E3: Neha | F3: Laptop | G3: Electronics | H3: 3 | I3: 21400 | K3: 6742
A4: ORD0003 | B4: 45624 | C4: East | D4: GJ | E4: Karan | F4: Laptop | G4: Electronics | H4: 6 | I4: 40298
A5: ORD0004 | B5: 45311 | C5: North | D5: MH | E5: Rahul | F5: Monitor | G5: Electronics | H5: 9 | I5: 1098 | K5: 7334
A6: ORD0005 | B6: 45632 | C6: West | D6: RJ | E6: Karan | F6: Chair | G6: Furniture | H6: 4 | I6: 15968
A7: ORD0006 | B7: 45339 | C7: West | D7: RJ | E7: Amit | F7: Printer | G7: Electronics | H7: 10 | I7: 36961 | J7: 0.05 | K7: 16608
A8: ORD0007 | B8: 45618 | C8: North | D8: MH | E8: Amit | F8: Monitor | G8: Electronics | H8: 3 | I8: 1683 | K8: 25507
A9: ORD0008 | B9: 45476 | C9: South | D9: KA | E9: Amit | F9: Printer | G9: Electronics | H9: 2 | I9: 6047 | J9: 0.05
A10: ORD0009 | B10: 45530 | C10: North | D10: MH | E10: Amit | F10: Mouse | G10: Electronics | H10: 2 | I10: 3101 | J10: 0.1 | K10: 23538
A11: ORD0010 | B11: 45413 | C11: West | D11: MH | E11: Neha | F11: Printer | G11: Electronics | H11: 8 | I11: 41602 | J11: 0 | K11: 29885
A12: ORD0011 | B12: 45649 | C12: West | D12: GJ | E12: Karan | F12: Laptop | G12: Electronics | H12: 2 | I12: 17931 | J12: 0.1
A13: ORD0012 | B13: 45443 | C13: West | D13: TN | E13: Rahul | F13: Printer | G13: Electronics | H13: 3 | I13: 571 | J13: 0.1
A14: ORD0013 | B14: 45423 | C14: West | D14: MH | E14: Karan | F14: Chair | G14: Furniture | H14: 9 | I14: 28406 | J14: 0.1
A15: ORD0014 | B15: 45400 | C15: North | D15: GJ | E15: Neha | F15: Laptop | G15: Electronics | H15: 6 | I15: 39809 | K15: 7704
A16: ORD0015 | B16: 45549 | C16: East | D16: GJ | E16: Karan | F16: Chair | G16: Furniture | H16: 3 | I16: 17089 | J16: 0.05
A17: ORD0016 | B17: 45401 | C17: East | D17: RJ | E17: Priya | F17: Monitor | G17: Electronics | H17: 9 | I17: 24048 | J17: 0
A18: ORD0017 | B18: 45342 | C18: North | D18: MH | E18: Neha | F18: Desk | G18: Furniture | H18: 6 | I18: 6121 | J18: 0 | K18: 8273
A19: ORD0018 | B19: 45388 | C19: North | D19: DL | E19: Neha | F19: Laptop | G19: Electronics | H19: 8 | I19: 29203 | J19: 0.05
A20: ORD0019 | B20: 45570 | C20: East | D20: GJ | E20: Neha | F20: Printer | G20: Electronics | H20: 6 | I20: 25953
A21: ORD0020 | B21: 45412 | C21: North | D21: GJ | E21: Karan | F21: Chair | G21: Furniture | H21: 9 | I21: 38450 | J21: 0
A22: ORD0021 | B22: 45626 | C22: West | D22: GJ | E22: Neha | F22: Printer | G22: Electronics | H22: 10 | I22: 14948 | J22: 0.05 | K22: 29773
A23: ORD0022 | B23: 45491 | C23: West | D23: DL | E23: Rahul | F23: Desk | G23: Furniture | H23: 10 | I23: 11429 | J23: 0.05
A24: ORD0023 | B24: 45479 | C24: East | D24: DL | E24: Priya | F24: Mouse | G24: Electronics | H24: 5 | I24: 11682 | J24: 0.1
A25: ORD0024 | B25: 45415 | C25: West | D25: MH | E25: Karan | F25: Printer | G25: Electronics | H25: 1 | I25: 43628 | J25: 0.05
A26: ORD0025 | B26: 45349 | C26: West | D26: TN | E26: Neha | F26: Monitor | G26: Electronics | H26: 2 | I26: 49900 | J26: 0
A27: ORD0026 | B27: 45618 | C27: East | D27: GJ | E27: Amit | F27: Desk | G27: Furniture | H27: 9 | I27: 25307 | K27: 7356
A28: ORD0027 | B28: 45655 | C28: East | D28: RJ | E28: Rahul | F28: Monitor | G28: Electronics | H28: 9 | I28: 47015 | J28: 0 | K28: 27705
A29: ORD0028 | B29: 45638 | C29: East | D29: RJ | E29: Neha | F29: Monitor | G29: Electronics | H29: 4 | I29: 34893 | J29: 0.1
A30: ORD0029 | B30: 45315 | C30: South | D30: DL | E30: Amit | F30: Chair | G30: Furniture | H30: 9 | I30: 26283
A31: ORD0030 | B31: 45544 | C31: South | D31: TN | E31: Amit | F31: Laptop | G31: Electronics | H31: 2 | I31: 26513 | J31: 0.1
A32: ORD0031 | B32: 45529 | C32: North | D32: GJ | E32: Amit | F32: Laptop | G32: Electronics | H32: 9 | I32: 49552 | J32: 0.1 | K32: 22087
A33: ORD0032 | B33: 45479 | C33: North | D33: DL | E33: Karan | F33: Monitor | G33: Electronics | H33: 6 | I33: 26441 | K33: 21986
A34: ORD0033 | B34: 45561 | C34: South | D34: RJ | E34: Rahul | F34: Printer | G34: Electronics | H34: 9 | I34: 30588 | J34: 0.1 | K34: 22011
A35: ORD0034 | B35: 45336 | C35: West | D35: TN | E35: Rahul | F35: Monitor | G35: Electronics | H35: 9 | I35: 27695
A36: ORD0035 | B36: 45642 | C36: West | D36: MH | E36: Karan | F36: Printer | G36: Electronics | H36: 2 | I36: 10738 | J36: 0 | K36: 5576
A37: ORD0036 | B37: 45336 | C37: West | D37: MH | E37: Rahul | F37: Monitor | G37: Electronics | H37: 6 | I37: 7619 | K37: 13277
A38: ORD0037 | B38: 45346 | C38: West | D38: GJ | E38: Neha | F38: Laptop | G38: Electronics | H38: 8 | I38: 37570
A39: ORD0038 | B39: 45560 | C39: East | D39: GJ | E39: Neha | F39: Printer | G39: Electronics | H39: 1 | I39: 12074 | J39: 0.1
A40: ORD0039 | B40: 45397 | C40: South | D40: TN | E40: Priya | F40: Printer | G40: Electronics | H40: 1 | I40: 44737 | J40: 0.1 | K40: 24975
A41: ORD0040 | B41: 45329 | C41: North | D41: DL | E41: Karan | F41: Mouse | G41: Electronics | H41: 8 | I41: 19251 | J41: 0.05 | K41: 26894
A42: ORD0041 | B42: 45591 | C42: South | D42: RJ | E42: Amit | F42: Desk | G42: Furniture | H42: 3 | I42: 48694 | J42: 0 | K42: 6974
A43: ORD0042 | B43: 45620 | C43: North | D43: MH | E43: Karan | F43: Chair | G43: Furniture | H43: 1 | I43: 35665 | J43: 0.1
A44: ORD0043 | B44: 45455 | C44: South | D44: MH | E44: Rahul | F44: Chair | G44: Furniture | H44: 1 | I44: 18940 | J44: 0
A45: ORD0044 | B45: 45349 | C45: West | D45: DL | E45: Amit | F45: Printer | G45: Electronics | H45: 3 | I45: 672 | J45: 0.05 | K45: 16590
A46: ORD0045 | B46: 45539 | C46: North | D46: TN | E46: Amit | F46: Chair | G46: Furniture | H46: 1 | I46: 18649 | J46: 0.1 | K46: 9880
A47: ORD0046 | B47: 45428 | C47: West | D47: KA | E47: Rahul | F47: Chair | G47: Furniture | H47: 4 | I47: 12994 | K47: 969
A48: ORD0047 | B48: 45432 | C48: South | D48: KA | E48: Priya | F48: Chair | G48: Furniture | H48: 8 | I48: 9668 | J48: 0.1
A49: ORD0048 | B49: 45518 | C49: North | D49: RJ | E49: Priya | F49: Monitor | G49: Electronics | H49: 6 | I49: 38361 | J49: 0
A50: ORD0049 | B50: 45454 | C50: East | D50: DL | E50: Rahul | F50: Desk | G50: Furniture | H50: 4 | I50: 2202 | J50: 0.05 | K50: 25372
A51: ORD0050 | B51: 45639 | C51: West | D51: TN | E51: Neha | F51: Mouse | G51: Electronics | H51: 7 | I51: 43713 | J51: 0.1
A52: ORD0051 | B52: 45399 | C52: West | D52: DL | E52: Priya | F52: Laptop | G52: Electronics | H52: 8 | I52: 1172
A53: ORD0052 | B53: 45568 | C53: East | D53: DL | E53: Rahul | F53: Monitor | G53: Electronics | H53: 2 | I53: 28932 | K53: 19839
A54: ORD0053 | B54: 45379 | C54: South | D54: GJ | E54: Priya | F54: Printer | G54: Electronics | H54: 9 | I54: 12134 | J54: 0
A55: ORD0054 | B55: 45619 | C55: South | D55: RJ | E55: Karan | F55: Chair | G55: Furniture | H55: 6 | I55: 28535 | J55: 0.05
A56: ORD0055 | B56: 45367 | C56: East | D56: KA | E56: Neha | F56: Printer | G56: Electronics | H56: 10 | I56: 18292
A57: ORD0056 | B57: 45453 | C57: East | D57: GJ | E57: Amit | F57: Monitor | G57: Electronics | H57: 1 | I57: 21732 | J57: 0.1 | K57: 3127
A58: ORD0057 | B58: 45612 | C58: North | D58: TN | E58: Priya | F58: Printer | G58: Electronics | H58: 9 | I58: 33284 | J58: 0.05
A59: ORD0058 | B59: 45589 | C59: North | D59: DL | E59: Neha | F59: Laptop | G59: Electronics | H59: 7 | I59: 10389 | K59: 22159
A60: ORD0059 | B60: 45326 | C60: East | D60: RJ | E60: Amit | F60: Chair | G60: Furniture | H60: 9 | I60: 5625 | K60: 9293
A61: ORD0060 | B61: 45606 | C61: South | D61: DL | E61: Rahul | F61: Mouse | G61: Electronics | H61: 7 | I61: 40540 | J61: 0
A62: ORD0061 | B62: 45596 | C62: West | D62: RJ | E62: Amit | F62: Desk | G62: Furniture | H62: 2 | I62: 1279 | J62: 0.05 | K62: 7957
A63: ORD0062 | B63: 45475 | C63: North | D63: RJ | E63: Amit | F63: Mouse | G63: Electronics | H63: 7 | I63: 16631 | J63: 0.1 | K63: 4214
A64: ORD0063 | B64: 45558 | C64: North | D64: RJ | E64: Rahul | F64: Chair | G64: Furniture | H64: 7 | I64: 32756 | J64: 0 | K64: 16465
A65: ORD0064 | B65: 45562 | C65: North | D65: MH | E65: Karan | F65: Printer | G65: Electronics | H65: 7 | I65: 22550 | J65: 0.1
A66: ORD0065 | B66: 45636 | C66: North | D66: RJ | E66: Amit | F66: Desk | G66: Furniture | H66: 8 | I66: 22339 | J66: 0 | K66: 2121
A67: ORD0066 | B67: 45507 | C67: West | D67: KA | E67: Amit | F67: Laptop | G67: Electronics | H67: 2 | I67: 46159 | J67: 0.05
A68: ORD0067 | B68: 45328 | C68: North | D68: DL | E68: Karan | F68: Desk | G68: Furniture | H68: 6 | I68: 22125 | J68: 0 | K68: 29712
A69: ORD0068 | B69: 45594 | C69: South | D69: GJ | E69: Karan | F69: Mouse | G69: Electronics | H69: 6 | I69: 41323 | K69: 17325
A70: ORD0069 | B70: 45300 | C70: West | D70: RJ | E70: Neha | F70: Desk | G70: Furniture | H70: 3 | I70: 28541 | J70: 0.1 | K70: 6771
A71: ORD0070 | B71: 45582 | C71: South | D71: DL | E71: Amit | F71: Chair | G71: Furniture | H71: 7 | I71: 16466 | K71: 22928
A72: ORD0071 | B72: 45310 | C72: East | D72: DL | E72: Rahul | F72: Desk | G72: Furniture | H72: 2 | I72: 12316
A73: ORD0072 | B73: 45491 | C73: West | D73: MH | E73: Amit | F73: Desk | G73: Furniture | H73: 10 | I73: 34687 | K73: 10859
A74: ORD0073 | B74: 45626 | C74: East | D74: KA | E74: Amit | F74: Desk | G74: Furniture | H74: 4 | I74: 32319 | J74: 0.05 | K74: 20290
A75: ORD0074 | B75: 45323 | C75: North | D75: KA | E75: Priya | F75: Monitor | G75: Electronics | H75: 1 | I75: 1976 | J75: 0.05 | K75: 5597
A76: ORD0075 | B76: 45336 | C76: South | D76: RJ | E76: Amit | F76: Printer | G76: Electronics | H76: 4 | I76: 27237 | J76: 0 | K76: 17550
A77: ORD0076 | B77: 45424 | C77: South | D77: DL | E77: Amit | F77: Mouse | G77: Electronics | H77: 8 | I77: 36429 | J77: 0.05 | K77: 15686
A78: ORD0077 | B78: 45579 | C78: East | D78: DL | E78: Rahul | F78: Chair | G78: Furniture | H78: 7 | I78: 30010 | J78: 0 | K78: 6503
A79: ORD0078 | B79: 45351 | C79: East | D79: GJ | E79: Neha | F79: Laptop | G79: Electronics | H79: 2 | I79: 15440 | J79: 0.1 | K79: 18884
A80: ORD0079 | B80: 45339 | C80: South | D80: KA | E80: Neha | F80: Mouse | G80: Electronics | H80: 1 | I80: 26526 | J80: 0.05
A81: ORD0080 | B81: 45303 | C81: South | D81: DL | E81: Priya | F81: Mouse | G81: Electronics | H81: 10 | I81: 41127 | J81: 0.05 | K81: 2039
A82: ORD0081 | B82: 45596 | C82: North | D82: MH | E82: Neha | F82: Mouse | G82: Electronics | H82: 7 | I82: 5533 | J82: 0.05
A83: ORD0082 | B83: 45310 | C83: North | D83: MH | E83: Amit | F83: Chair | G83: Furniture | H83: 1 | I83: 4265 | J83: 0.1
A84: ORD0083 | B84: 45495 | C84: East | D84: KA | E84: Karan | F84: Monitor | G84: Electronics | H84: 1 | I84: 40542
A85: ORD0084 | B85: 45421 | C85: South | D85: KA | E85: Neha | F85: Printer | G85: Electronics | H85: 1 | I85: 10295 | K85: 9606
A86: ORD0085 | B86: 45614 | C86: East | D86: GJ | E86: Karan | F86: Mouse | G86: Electronics | H86: 10 | I86: 43135
A87: ORD0086 | B87: 45428 | C87: East | D87: RJ | E87: Priya | F87: Printer | G87: Electronics | H87: 3 | I87: 22790 | J87: 0.05
A88: ORD0087 | B88: 45311 | C88: West | D88: MH | E88: Neha | F88: Laptop | G88: Electronics | H88: 10 | I88: 36203 | J88: 0.05 | K88: 4593
A89: ORD0088 | B89: 45452 | C89: West | D89: KA | E89: Neha | F89: Chair | G89: Furniture | H89: 2 | I89: 29990 | J89: 0
A90: ORD0089 | B90: 45402 | C90: South | D90: KA | E90: Rahul | F90: Desk | G90: Furniture | H90: 2 | I90: 34584
A91: ORD0090 | B91: 45332 | C91: North | D91: DL | E91: Amit | F91: Desk | G91: Furniture | H91: 8 | I91: 6065 | J91: 0.05 | K91: 11003
A92: ORD0091 | B92: 45651 | C92: North | D92: MH | E92: Rahul | F92: Printer | G92: Electronics | H92: 9 | I92: 35616 | K92: 14753
A93: ORD0092 | B93: 45542 | C93: North | D93: GJ | E93: Neha | F93: Monitor | G93: Electronics | H93: 7 | I93: 14701 | J93: 0.05
A94: ORD0093 | B94: 45592 | C94: East | D94: TN | E94: Neha | F94: Printer | G94: Electronics | H94: 8 | I94: 11159 | K94: 959
A95: ORD0094 | B95: 45471 | C95: North | D95: KA | E95: Rahul | F95: Monitor | G95: Electronics | H95: 6 | I95: 39961 | J95: 0.1 | K95: 24009
A96: ORD0095 | B96: 45383 | C96: West | D96: KA | E96: Rahul | F96: Printer | G96: Electronics | H96: 9 | I96: 12105 | J96: 0.05
A97: ORD0096 | B97: 45516 | C97: West | D97: MH | E97: Neha | F97: Chair | G97: Furniture | H97: 4 | I97: 18667 | J97: 0.1 | K97: 13662
A98: ORD0097 | B98: 45390 | C98: North | D98: GJ | E98: Amit | F98: Printer | G98: Electronics | H98: 9 | I98: 30848 | J98: 0.1 | K98: 24623
A99: ORD0098 | B99: 45345 | C99: South | D99: KA | E99: Amit | F99: Laptop | G99: Electronics | H99: 9 | I99: 2772 | J99: 0.05 | K99: 969
A100: ORD0099 | B100: 45366 | C100: North | D100: MH | E100: Karan | F100: Chair | G100: Furniture | H100: 9 | I100: 30646 | J100: 0
...

Sheet Lookup_Tables
A1: Product | B1: Category | C1: Cost
A2: Laptop | B2: Electronics | C2: 19265
A3: Mouse | B3: Electronics | C3: 28046
A4: Chair | B4: Furniture | C4: 13271
A5: Desk | B5: Furniture | C5: 13040
A6: Printer | B6: Electronics | C6: 7384
A7: Monitor | B7: Electronics | C7: 2888
A9: Region | B9: Target
A10: North | B10: 484968
A11: South | B11: 302462
A12: East | B12: 574404
A13: West | B13: 539344
